lab_main/lab_0/dti_updown_count.v
module dti_updown_count #(
    parameter COUNT_WIDTH = 8
)(
    input                        clk,
    input                        reset_n,
    input  [COUNT_WIDTH-1:0]     count_to,
    input                        count_inc,
    input                        count_dec,
    output                       flag_count_max,
    output                       flag_count_min,
    output reg [COUNT_WIDTH-1:0] count
);

    always @(posedge clk or negedge reset_n) begin
        if (!reset_n) begin
            count <= 0;
        end
        else begin
            case ({count_inc, count_dec})
                2'b00: count <= count;
                2'b01: if (count > 0) count <= count - 1;
                2'b10: if (count < count_to) count <= count + 1;
                2'b11: count <= count;
            endcase
        end
    end

    assign flag_count_min = (count == 0);
    assign flag_count_max = (count == count_to);

endmodule

lab_main/lab_0/dti_updown_count_tb.v
`timescale 1ns/1ps

module tb_dti_updown_count;
    parameter COUNT_WIDTH = 8;

    reg clk;
    reg reset_n;
    reg [COUNT_WIDTH-1:0] count_to;
    reg count_inc;
    reg count_dec;
    wire flag_count_max;
    wire flag_count_min;
    wire [COUNT_WIDTH-1:0] count;

    dti_updown_count #(
        .COUNT_WIDTH(COUNT_WIDTH)
    ) uut (
        .clk(clk),
        .reset_n(reset_n),
        .count_to(count_to),
        .count_inc(count_inc),
        .count_dec(count_dec),
        .flag_count_max(flag_count_max),
        .flag_count_min(flag_count_min),
        .count(count)
    );

    initial begin
        clk = 0;
        forever #5 clk = ~clk;
    end

    always @(posedge clk) begin
        $display("Time=%0t ns | count=%0d | inc=%b | dec=%b | max=%b | min=%b | count_to=%0d",
                 $time, count, count_inc, count_dec, flag_count_max, flag_count_min, count_to);
    end

    initial begin
        $dumpfile("updown_counter.vcd");
        $dumpvars(0, tb_dti_updown_count);

        reset_n = 0;
        count_inc = 0;
        count_dec = 0;
        count_to  = 8'd10;
        #20;
        reset_n = 1;  
        #10;

        $display("=== TEST 1: COUNT UP ===");
        count_inc = 1;
        repeat (12) @(posedge clk);
        count_inc = 0;
        #20;

        $display("=== TEST 2: COUNT DOWN ===");
        count_dec = 1;
        repeat (5) @(posedge clk);
        count_dec = 0;
        #20;

        $display("=== TEST 3: INC + DEC ACTIVE ===");
        count_inc = 1;
        count_dec = 1;
        repeat (5) @(posedge clk);
        count_inc = 0;
        count_dec = 0;
        #20;

        $display("=== TEST 4: RESET MID-RUN ===");
        count_inc = 1;
        repeat (5) @(posedge clk);
        reset_n = 0; #10;
        reset_n = 1; #10;
        count_inc = 0;

        #50;
        $display("Simulation finished at %0t ns", $time);
        $finish;
    end
endmodule

lab_main/lab_0_0410_basic/updown_counter.vcd
$date
	Sat Oct 18 15:36:58 2025
$end
$version
	QuestaSim Version 2024.1
$end
$timescale
	1ps
$end

$scope module tb_dti_updown_count $end
$var parameter 32 ! COUNT_WIDTH $end
$var reg 1 " clk $end
$var reg 1 # reset_n $end
$var reg 8 $ count_to [7:0] $end
$var reg 1 % count_inc $end
$var reg 1 & count_dec $end
$var wire 1 ' flag_count_max $end
$var wire 1 ( flag_count_min $end
$var wire 1 ) count [7] $end
$var wire 1 * count [6] $end
$var wire 1 + count [5] $end
$var wire 1 , count [4] $end
$var wire 1 - count [3] $end
$var wire 1 . count [2] $end
$var wire 1 / count [1] $end
$var wire 1 0 count [0] $end

$scope module uut $end
$var parameter 32 1 COUNT_WIDTH $end
$var wire 1 2 clk $end
$var wire 1 3 reset_n $end
$var wire 1 4 count_to [7] $end
$var wire 1 5 count_to [6] $end
$var wire 1 6 count_to [5] $end
$var wire 1 7 count_to [4] $end
$var wire 1 8 count_to [3] $end
$var wire 1 9 count_to [2] $end
$var wire 1 : count_to [1] $end
$var wire 1 ; count_to [0] $end
$var wire 1 < count_inc $end
$var wire 1 = count_dec $end
$var wire 1 ' flag_count_max $end
$var wire 1 ( flag_count_min $end
$var reg 8 > count [7:0] $end
$upscope $end
$upscope $end
$enddefinitions $end
#0
$dumpvars
0"
0#
b1010 $
0%
0&
b0 >
b1000 !
b1000 1
0'
1(
00
0/
0.
0-
0,
0+
0*
0)
0=
0<
0;
1:
09
18
07
06
05
04
03
02
$end
#5000
1"
12
#10000
0"
02
#15000
1"
12
#20000
1#
0"
13
02
#25000
1"
12
#30000
1%
0"
1<
02
#35000
1"
12
b1 >
0(
10
#40000
0"
02
#45000
1"
12
b10 >
00
1/
#50000
0"
02
#55000
1"
12
b11 >
10
#60000
0"
02
#65000
1"
12
b100 >
00
0/
1.
#70000
0"
02
#75000
1"
12
b101 >
10
#80000
0"
02
#85000
1"
12
b110 >
00
1/
#90000
0"
02
#95000
1"
12
b111 >
10
#100000
0"
02
#105000
1"
12
b1000 >
00
0/
0.
1-
#110000
0"
02
#115000
1"
12
b1001 >
10
#120000
0"
02
#125000
1"
12
b1010 >
1'
00
1/
#130000
0"
02
#135000
1"
12
#140000
0"
02
#145000
1"
12
0%
0<
#150000
0"
02
#155000
1"
12
#160000
0"
02
#165000
1&
1"
1=
12
b1001 >
0'
10
0/
#170000
0"
02
#175000
1"
12
b1000 >
00
#180000
0"
02
#185000
1"
12
b111 >
10
1/
1.
0-
#190000
0"
02
#195000
1"
12
b110 >
00
#200000
0"
02
#205000
1"
12
0&
0=
b101 >
10
0/
#210000
0"
02
#215000
1"
12
#220000
0"
02
#225000
1%
1&
1"
1<
1=
12
#230000
0"
02
#235000
1"
12
#240000
0"
02
#245000
1"
12
#250000
0"
02
#255000
1"
12
#260000
0"
02
#265000
1"
12
0%
0&
0<
0=
#270000
0"
02
#275000
1"
12
#280000
0"
02
#285000
1%
1"
1<
12
b110 >
00
1/
#290000
0"
02
#295000
1"
12
b111 >
10
#300000
0"
02
#305000
1"
12
b1000 >
00
0/
0.
1-
#310000
0"
02
#315000
1"
12
b1001 >
10
#320000
0"
02
#325000
1"
12
0#
03
b1010 >
b0 >
1(
00
0-
#330000
0"
02
#335000
1#
1"
13
12
b1 >
0(
10
#340000
0"
02
#345000
0%
1"
0<
12
